matlearn/__init__.py
matlearn/_errors.py
matlearn/evaluation.py
matlearn/models.py
matlearn/preprocessing.py
matlearn-1.0.0.3.dist-info/LICENSE
matlearn-1.0.0.3.dist-info/METADATA
matlearn-1.0.0.3.dist-info/WHEEL
matlearn-1.0.0.3.dist-info/top_level.txt
matlearn-1.0.0.3.dist-info/RECORD
