Metadata-Version: 2.1
Name: matlearn
Version: 1.0.0.3
Summary: Matlearn can train machine learning models and comes in three major parts : preprocessing, training, and evaluation.
Home-page: https://github.com/itsMahdiZare/matlearn
Author: Mahdi Zare
Author-email: itsmahdizare@gmail.com
License: UNKNOWN
Project-URL: Bug Tracker, https://github.com/itsMahdiZare/matlearn/issues
Platform: UNKNOWN
Classifier: Programming Language :: Python :: 3
Classifier: License :: OSI Approved :: MIT License
Classifier: Operating System :: OS Independent
Requires-Python: >=3.6
License-File: LICENSE
Requires-Dist: numpy
